IpmiLibrary/__init__.py
IpmiLibrary/bmc.py
IpmiLibrary/chassis.py
IpmiLibrary/fru.py
IpmiLibrary/hpm.py
IpmiLibrary/lan.py
IpmiLibrary/mapping.py
IpmiLibrary/picmg.py
IpmiLibrary/sdr.py
IpmiLibrary/sel.py
IpmiLibrary/utils.py
IpmiLibrary/version.py
robotframework_ipmilibrary-0.3.7.dist-info/licenses/AUTHORS
robotframework_ipmilibrary-0.3.7.dist-info/licenses/COPYING
robotframework_ipmilibrary-0.3.7.dist-info/METADATA
robotframework_ipmilibrary-0.3.7.dist-info/WHEEL
robotframework_ipmilibrary-0.3.7.dist-info/top_level.txt
robotframework_ipmilibrary-0.3.7.dist-info/RECORD
