Metadata-Version: 2.4
Name: robotframework-ipmilibrary
Version: 0.3.7
Summary: IPMI Library for Robot Framework
Home-page: https://github.com/kontron/robotframework-ipmilibrary
Download-URL: https://pypi.python.org/pypi/robotframework-ipmilibrary
Author: Michael Walle, Heiko Thiery
Author-email: michael.walle@kontron.com, heiko.thiery@kontron.com
License: Apache License 2.0
Classifier: Development Status :: 4 - Beta
Classifier: Framework :: Robot Framework
Classifier: License :: OSI Approved :: Apache Software License
Classifier: Operating System :: OS Independent
Classifier: Programming Language :: Python
Classifier: Topic :: Software Development :: Testing
License-File: COPYING
License-File: AUTHORS
Requires-Dist: robotframework
Requires-Dist: python-ipmi
Dynamic: author
Dynamic: author-email
Dynamic: classifier
Dynamic: description
Dynamic: download-url
Dynamic: home-page
Dynamic: license
Dynamic: license-file
Dynamic: requires-dist
Dynamic: summary
